mytflib/DataLoader.py
mytflib/LR_Shaper.py
mytflib/LR_Tuner.py
mytflib/TFrec_Curator.py
mytflib/Train_Manager.py
mytflib/__init__.py
mytflib-0.0.2.0.dist-info/METADATA
mytflib-0.0.2.0.dist-info/WHEEL
mytflib-0.0.2.0.dist-info/top_level.txt
mytflib-0.0.2.0.dist-info/RECORD
