Metadata-Version: 2.1
Name: mytflib
Version: 0.0.2.0
Summary: My TensorFlow Library
Home-page: https://github.com/johnypark/mytflib
Author: John Park
Author-email: parkjohnyc@gmail.com
License: UNKNOWN
Platform: UNKNOWN
Classifier: Programming Language :: Python :: 3
Classifier: License :: OSI Approved :: MIT License
Classifier: Operating System :: OS Independent
Requires-Python: >=3.6
Requires-Dist: tensorflow
Requires-Dist: opencv-python
Requires-Dist: tensorflow-addons
